{
    "courseOfferings": [
        {
            "offeringUnit": {
                "code": "01"
            },
            "course": {
                "subject": "667",
                "number": "387"
            },
            "supplementCode": "  ",
            "campusCode": "NB",
            "synopsisUrl": "https://medieval-studies.rutgers.edu/academics/undergraduate/course-offerings",
            "courseNotes": null,
            "unitNotes": null,
            "subjectNotes": null,
            "subjectGroupNotes": null,
            "prereqNotes": null,
            "coreCodes": null,
            "courseFee": null,
            "title": "TOUCHING HISTORY",
            "fullTitle": "TOUCHING HISTORY: THE WORLD OF MEDIEVAL MANUSCRIPTS                             ",
            "credits": "3",
            "sections": [
                {
                    "yearterm": "20259",
                    "registrationIndex": "22879",
                    "legendKey": null,
                    "sectionNumber": "01",
                    "sectionNotes": null,
                    "subtitleText": null,
                    "subtopicText": null,
                    "sectionEligibility": null,
                    "examCode": "C",
                    "sessionDates": null,
                    "open": true,
                    "sectionCourseType": "T",
                    "specialPermissionAdd": null,
                    "comments": [],
                    "meetingTimes": [
                        {
                            "baClassHours": "",
                            "meetingDay": "Monday",
                            "startMinute": "950",
                            "endMinute": "1030",
                            "buildingCode": "MH",
                            "buildingNum": null,
                            "roomNumber": "115",
                            "meetingModeCode": "02",
                            "meetingModeDesc": "LEC",
                            "campusAbbrev": "College Avenue",
                            "campusName": "College Avenue",
                            "campusLocation": "1"
                        },
                        {
                            "baClassHours": "",
                            "meetingDay": "Wednesday",
                            "startMinute": "950",
                            "endMinute": "1030",
                            "buildingCode": "MH",
                            "buildingNum": null,
                            "roomNumber": "115",
                            "meetingModeCode": "02",
                            "meetingModeDesc": "LEC",
                            "campusAbbrev": "College Avenue",
                            "campusName": "College Avenue",
                            "campusLocation": "1"
                        }
                    ],
                    "instructors": [
                        {
                            "name": "RENDSBURG, GARY"
                        }
                    ],
                    "crossListedSections": [
                        {
                            "course": "01:506:388:01"
                        },
                        {
                            "course": "01:840:388:01"
                        },
                        {
                            "course": "01:563:387:01"
                        }
                    ],
                    "majors": []
                }
            ]
        },
        {
            "offeringUnit": {
                "code": "01"
            },
            "course": {
                "subject": "667",
                "number": "390"
            },
            "supplementCode": "  ",
            "campusCode": "NB",
            "synopsisUrl": "https://medieval-studies.rutgers.edu/academics/undergraduate/course-offerings",
            "courseNotes": null,
            "unitNotes": null,
            "subjectNotes": null,
            "subjectGroupNotes": null,
            "prereqNotes": null,
            "coreCodes": null,
            "courseFee": null,
            "title": "INDEPENDENT STUDY",
            "fullTitle": "INDEPENDENT STUDY",
            "credits": "3",
            "sections": [
                {
                    "yearterm": "20259",
                    "registrationIndex": "11598",
                    "legendKey": null,
                    "sectionNumber": "01",
                    "sectionNotes": null,
                    "subtitleText": null,
                    "subtopicText": null,
                    "sectionEligibility": null,
                    "examCode": "A",
                    "sessionDates": null,
                    "open": true,
                    "sectionCourseType": "T",
                    "specialPermissionAdd": " Department staff",
                    "comments": [
                        "Go to http://canvas.rutgers.edu"
                    ],
                    "meetingTimes": [
                        {
                            "baClassHours": "B",
                            "meetingDay": null,
                            "startMinute": null,
                            "endMinute": null,
                            "buildingCode": "",
                            "buildingNum": null,
                            "roomNumber": "",
                            "meetingModeCode": "19",
                            "meetingModeDesc": "PROJ-IND",
                            "campusAbbrev": "",
                            "campusName": "",
                            "campusLocation": ""
                        }
                    ],
                    "instructors": [
                        {
                            "name": "NOVACICH, SARAH"
                        }
                    ],
                    "crossListedSections": [],
                    "majors": []
                }
            ]
        }
    ]
}